{
  "first": {},
  "title": "Apie mus",
  "description": "UAB Elistroy yra patikima statybų įmonė, kuri veikia Lietuvoje jau daugiau nei 3 metus. Mes esam profesionalūs statybininkai, kurie gali atlikti visų rūšių statybos darbus, nuo namų statybos iki komercinių projektų. Taip pat siūlome konsultacijas, projektavimo paslaugas ir techninę pagalbą. Mes siekiame suteikti aukščiausios kokybės paslaugas, kurios atitinka visus klientų reikalavimus. Užtikriname, kad visi mūsų darbai būtų atliekami laiku ir pagal nustatytą biudžetą.",
  "buttonName": "Susisiekite jau dabar!",
  "year": "3 metų patirtis",
  "suggestions": ["Sąžininga kaina", "Atliktų darbų garantija", "Profesonalus darbų vykdymas"]
}
